[
    {
        "key": "datr",
        "value": "KInVZvGaMQAv1BS1TondhC1T",
        "domain": "facebook.com",
        "path": "/",
        "hostOnly": false,
        "creation": "2024-09-02T10:46:17.822Z",
        "lastAccessed": "2024-09-02T10:46:17.822Z"
    },
    {
        "key": "sb",
        "value": "KInVZjceq81RqtF80Ka0L-1I",
        "domain": "facebook.com",
        "path": "/",
        "hostOnly": false,
        "creation": "2024-09-02T10:46:17.822Z",
        "lastAccessed": "2024-09-02T10:46:17.822Z"
    },
    {
        "key": "m_pixel_ratio",
        "value": "1.5303868055343628",
        "domain": "facebook.com",
        "path": "/",
        "hostOnly": false,
        "creation": "2024-09-02T10:46:17.822Z",
        "lastAccessed": "2024-09-02T10:46:17.822Z"
    },
    {
        "key": "c_user",
        "value": "61553676575943",
        "domain": "facebook.com",
        "path": "/",
        "hostOnly": false,
        "creation": "2024-09-02T10:46:17.822Z",
        "lastAccessed": "2024-09-02T10:46:17.822Z"
    },
    {
        "key": "fr",
        "value": "0CZwhE7hxpm8PEPya.AWWr1qO1JJLf6vg-e3hfrYAUkYM.Bm1Yko..AAA.0.0.Bm1YlV.AWVE7vyoxHo",
        "domain": "facebook.com",
        "path": "/",
        "hostOnly": false,
        "creation": "2024-09-02T10:46:17.822Z",
        "lastAccessed": "2024-09-02T10:46:17.822Z"
    },
    {
        "key": "xs",
        "value": "37%3AC2a8st7SLaT04Q%3A2%3A1725270357%3A-1%3A5170",
        "domain": "facebook.com",
        "path": "/",
        "hostOnly": false,
        "creation": "2024-09-02T10:46:17.822Z",
        "lastAccessed": "2024-09-02T10:46:17.822Z"
    },
    {
        "key": "locale",
        "value": "en_GB",
        "domain": "facebook.com",
        "path": "/",
        "hostOnly": false,
        "creation": "2024-09-02T10:46:17.822Z",
        "lastAccessed": "2024-09-02T10:46:17.822Z"
    },
    {
        "key": "vpd",
        "value": "v1%3B747x400x1.5303868055343628",
        "domain": "facebook.com",
        "path": "/",
        "hostOnly": false,
        "creation": "2024-09-02T10:46:17.822Z",
        "lastAccessed": "2024-09-02T10:46:17.822Z"
    },
    {
        "key": "m_page_voice",
        "value": "61553676575943",
        "domain": "facebook.com",
        "path": "/",
        "hostOnly": false,
        "creation": "2024-09-02T10:46:17.822Z",
        "lastAccessed": "2024-09-02T10:46:17.822Z"
    },
    {
        "key": "wd",
        "value": "470x879",
        "domain": "facebook.com",
        "path": "/",
        "hostOnly": false,
        "creation": "2024-09-02T10:46:17.822Z",
        "lastAccessed": "2024-09-02T10:46:17.822Z"
    },
    {
        "key": "fbl_st",
        "value": "100434853%3BT%3A28754566",
        "domain": "facebook.com",
        "path": "/",
        "hostOnly": false,
        "creation": "2024-09-02T10:46:17.822Z",
        "lastAccessed": "2024-09-02T10:46:17.822Z"
    },
    {
        "key": "wl_cbv",
        "value": "v2%3Bclient_version%3A2609%3Btimestamp%3A1725273970",
        "domain": "facebook.com",
        "path": "/",
        "hostOnly": false,
        "creation": "2024-09-02T10:46:17.822Z",
        "lastAccessed": "2024-09-02T10:46:17.822Z"
    }
        ]
